{
  "TSM": {"manufacturer": "Škoda Auto", "country": "CZ", "plant": "Mladá Boleslav"},
  "TMB": {"manufacturer": "Škoda Auto", "country": "CZ", "plant": "Mladá Boleslav"},
  "TMP": {"manufacturer": "Škoda Auto", "country": "CZ", "plant": "Kvasiny"},
  "TM9": {"manufacturer": "Škoda Auto", "country": "CZ", "plant": "Kvasiny"},
  "VF3": {"manufacturer": "Peugeot", "country": "FR", "plant": "Sochaux"},
  "VF7": {"manufacturer": "Citroën", "country": "FR", "plant": "Vélizy"},
  "VF1": {"manufacturer": "Renault", "country": "FR", "plant": "Flins"},
  "W0L": {"manufacturer": "Opel", "country": "DE", "plant": "Rüsselsheim"},
  "ZFA": {"manufacturer": "Fiat", "country": "IT", "plant": "Turin"},
  "WVW": {"manufacturer": "Volkswagen", "country": "DE", "plant": "Wolfsburg"},
  "WVG": {"manufacturer": "Volkswagen", "country": "DE", "plant": "Wolfsburg"},
  "WV1": {"manufacturer": "Volkswagen", "country": "DE", "plant": "Commercial Vehicles"},
  "WAU": {"manufacturer": "Audi", "country": "DE", "plant": "Ingolstadt"},
  "TRU": {"manufacturer": "Audi", "country": "HU", "plant": "Győr"},
  "WBA": {"manufacturer": "BMW", "country": "DE", "plant": "Munich"},
  "5UX": {"manufacturer": "BMW", "country": "US", "plant": "Spartanburg"},
  "WDB": {"manufacturer": "Mercedes-Benz", "country": "DE", "plant": "Sindelfingen"},
  "WDC": {"manufacturer": "Mercedes-Benz", "country": "DE", "plant": "Bremen"},
  "WDD": {"manufacturer": "Mercedes-Benz", "country": "DE", "plant": "Rastatt"},
  "1FT": {"manufacturer": "Ford", "country": "US", "plant": "Michigan"},
  "1FM": {"manufacturer": "Ford", "country": "US", "plant": "Kentucky"},
  "WF0": {"manufacturer": "Ford", "country": "DE", "plant": "Cologne"},
  "VSS": {"manufacturer": "SEAT", "country": "ES", "plant": "Martorell"},
  "STM": {"manufacturer": "SEAT", "country": "ES", "plant": "Martorell"},
  "1HG": {"manufacturer": "Honda", "country": "US", "plant": "Ohio"},
  "JMZ": {"manufacturer": "Mazda", "country": "JP", "plant": "Hiroshima"},
  "WMW": {"manufacturer": "MINI", "country": "GB", "plant": "Oxford"},
  "KMH": {"manufacturer": "Hyundai", "country": "KR", "plant": "Ulsan"},
  "KNJ": {"manufacturer": "Kia", "country": "KR", "plant": "Sohari"},
  "TNZ": {"manufacturer": "Nissan", "country": "ES", "plant": "Barcelona"},
  "JN1": {"manufacturer": "Nissan", "country": "JP", "plant": "Yokosuka"},
  "JT": {"manufacturer": "Toyota", "country": "JP", "plant": "Toyota City"}
}

